tmtcrunch/__init__.py
tmtcrunch/altsp.py
tmtcrunch/astropy_stats.py
tmtcrunch/config.py
tmtcrunch/main.py
tmtcrunch/utils.py
tmtcrunch-2025.2.25.dist-info/LICENSE
tmtcrunch-2025.2.25.dist-info/METADATA
tmtcrunch-2025.2.25.dist-info/WHEEL
tmtcrunch-2025.2.25.dist-info/entry_points.txt
tmtcrunch-2025.2.25.dist-info/top_level.txt
tmtcrunch-2025.2.25.dist-info/RECORD
