Metadata-Version: 2.2
Name: tmtcrunch
Version: 2025.2.25
Summary: Python utility for TMT-based proteomics
Author-email: Max Brazhnikov <makc@issp.ac.ru>
Maintainer-email: Max Brazhnikov <makc@issp.ac.ru>
License: BSD-3-Clause
Project-URL: homepage, https://codeberg.org/makc/tmtcrunch
Project-URL: repository, https://codeberg.org/makc/tmtcrunch.git
Keywords: proteomics
Classifier: Development Status :: 4 - Beta
Classifier: Environment :: Console
Classifier: Intended Audience :: Science/Research
Classifier: License :: OSI Approved :: BSD License
Classifier: Programming Language :: Python
Classifier: Programming Language :: Python :: 3 :: Only
Classifier: Programming Language :: Python :: 3.10
Classifier: Programming Language :: Python :: 3.11
Classifier: Programming Language :: Python :: 3.12
Classifier: Topic :: Scientific/Engineering :: Bio-Informatics
Requires-Python: >=3.10
License-File: LICENSE
Requires-Dist: numpy
Requires-Dist: pandas
Requires-Dist: pyteomics
Requires-Dist: tomli; python_version < "3.11"
